iagitup/__init__.py
iagitup/__main__.py
iagitup/iagitup.py
iagitup-1.6.2.dist-info/METADATA
iagitup-1.6.2.dist-info/RECORD
iagitup-1.6.2.dist-info/WHEEL
iagitup-1.6.2.dist-info/entry_points.txt
iagitup-1.6.2.dist-info/top_level.txt
