Metadata-Version: 2.1
Name: iagitup
Version: 1.6.2
Summary: Tool to archive a git repository form GitHub to the Internet Archive.
Home-page: https://github.com/gdamdam/iagitup
Author: Giovanni Damiola
Author-email: UNKNOWN
License: GNU General Public License v3.0
Keywords: github internetarchive
Platform: POSIX
Classifier: Development Status :: 4 - Beta
Classifier: Intended Audience :: Developers
Classifier: Natural Language :: English
Classifier: License :: OSI Approved :: GNU General Public License v3 (GPLv3)
Classifier: Programming Language :: Python
Classifier: Programming Language :: Python :: 2.7
Requires-Dist: appdirs
Requires-Dist: args
Requires-Dist: asn1crypto
Requires-Dist: cffi
Requires-Dist: clint
Requires-Dist: cryptography
Requires-Dist: docopt
Requires-Dist: enum34
Requires-Dist: gitdb2
Requires-Dist: GitPython
Requires-Dist: idna
Requires-Dist: internetarchive
Requires-Dist: ipaddress
Requires-Dist: jsonpatch
Requires-Dist: markdown2
Requires-Dist: ndg-httpsclient
Requires-Dist: packaging
Requires-Dist: pyasn1
Requires-Dist: pycparser
Requires-Dist: pyOpenSSL
Requires-Dist: pyparsing
Requires-Dist: requests
Requires-Dist: schema
Requires-Dist: six
Requires-Dist: smmap2
Requires-Dist: wheel
